flipbook_generator.py
pdf2flipbook/__init__.py
pdf2flipbook/flipbook_generator.py
pdf2flipbook-0.1.2.dist-info/METADATA
pdf2flipbook-0.1.2.dist-info/WHEEL
pdf2flipbook-0.1.2.dist-info/entry_points.txt
pdf2flipbook-0.1.2.dist-info/top_level.txt
pdf2flipbook-0.1.2.dist-info/RECORD
