Metadata-Version: 2.1
Name: pdf2flipbook
Version: 0.1.2
Summary: Convert PDF to interactive HTML flipbook (self-contained, no external JS/CSS).
Home-page: UNKNOWN
Author: Dheeraj RP
License: UNKNOWN
Platform: UNKNOWN
Classifier: Programming Language :: Python :: 3.10
Requires-Dist: jinja2
Requires-Dist: pdf2image
Requires-Dist: pillow
